expyutil/__init__.py
expyutil/annotation.py
expyutil/dict.py
expyutil/hexStrBytes.py
expyutil/iter.py
expyutil/logging.py
expyutil/timer.py
expyutil/file_parser/__init__.py
expyutil/file_parser/base.py
expyutil/hexStrBytes/__init__.py
expyutil/hexStrBytes/hsb.py
expyutil/hexStrBytes/mask.py
expyutil/hexStrBytes/trans.py
expyutil-0.0.5.dist-info/METADATA
expyutil-0.0.5.dist-info/WHEEL
expyutil-0.0.5.dist-info/top_level.txt
expyutil-0.0.5.dist-info/RECORD
