Metadata-Version: 2.1
Name: expyutil
Version: 0.0.5
Summary: Description of your package
Author: tommyme
Author-email: your@email.com
